setup.py
pyrint/__init__.py
pyrint/progress.py
pyrint/pyrint.py
pyrint.egg-info/PKG-INFO
pyrint.egg-info/SOURCES.txt
pyrint.egg-info/dependency_links.txt
pyrint.egg-info/entry_points.txt
pyrint.egg-info/not-zip-safe
pyrint.egg-info/top_level.txt