Metadata-Version: 1.0
Name: pyrint
Version: 0.0.1
Summary: POS print utility. Copyright 2014 BOS Sales, LLC
Home-page: http://github.com/orderbliss/pyrint
Author: @orderbliss
Author-email: dev@orderbliss.com
License: Copyright 2014 Order Bliss
Platform: UNKNOWN
